batch_tamarin/__init__.py
batch_tamarin/main.py
batch_tamarin/runner.py
batch_tamarin/commands/__init__.py
batch_tamarin/commands/check.py
batch_tamarin/commands/init.py
batch_tamarin/commands/report.py
batch_tamarin/commands/run.py
batch_tamarin/model/__init__.py
batch_tamarin/model/batch.py
batch_tamarin/model/executable_task.py
batch_tamarin/model/report_data.py
batch_tamarin/model/tamarin_recipe.py
batch_tamarin/modules/__init__.py
batch_tamarin/modules/batch_manager.py
batch_tamarin/modules/cache_manager.py
batch_tamarin/modules/config_manager.py
batch_tamarin/modules/lemma_parser.py
batch_tamarin/modules/output_manager.py
batch_tamarin/modules/process_manager.py
batch_tamarin/modules/report_charts.py
batch_tamarin/modules/report_generator.py
batch_tamarin/modules/resource_manager.py
batch_tamarin/modules/tamarin_test_cmd.py
batch_tamarin/modules/task_manager.py
batch_tamarin/templates/report.html.j2
batch_tamarin/templates/report.md.j2
batch_tamarin/templates/report.tex.j2
batch_tamarin/templates/report.typ.j2
batch_tamarin/templates/summary.html.j2
batch_tamarin/utils/__init__.py
batch_tamarin/utils/compatibility_filter.py
batch_tamarin/utils/dot_utils.py
batch_tamarin/utils/model_checking.py
batch_tamarin/utils/notifications.py
batch_tamarin/utils/system_resources.py
batch_tamarin-1.1.1.dist-info/licenses/LICENSE
batch_tamarin-1.1.1.dist-info/METADATA
batch_tamarin-1.1.1.dist-info/WHEEL
batch_tamarin-1.1.1.dist-info/entry_points.txt
batch_tamarin-1.1.1.dist-info/top_level.txt
batch_tamarin-1.1.1.dist-info/RECORD
