Metadata-Version: 2.4
Name: batch-tamarin
Version: 1.1.1
Summary: Python wrapper for Tamarin Prover with JSON configuration
Author-email: Luca Mandrelli <luca.mandrelli@icloud.com>
License: GPL-3.0-or-later
Project-URL: Homepage, https://github.com/tamarin-prover/batch-tamarin
Project-URL: Repository, https://github.com/tamarin-prover/batch-tamarin
Project-URL: Documentation, https://github.com/tamarin-prover/batch-tamarin#readme
Project-URL: Bug Tracker, https://github.com/tamarin-prover/batch-tamarin/issues
Keywords: tamarin,prover,security,protocol,verification
Classifier: Development Status :: 4 - Beta
Classifier: Intended Audience :: Developers
Classifier: Intended Audience :: Science/Research
Classifier: License :: OSI Approved :: GNU General Public License v3 or later (GPLv3+)
Classifier: Operating System :: OS Independent
Classifier: Programming Language :: Python :: 3
Classifier: Programming Language :: Python :: 3.10
Classifier: Programming Language :: Python :: 3.11
Classifier: Programming Language :: Python :: 3.12
Classifier: Programming Language :: Python :: 3.13
Classifier: Programming Language :: Python :: 3.14
Classifier: Topic :: Scientific/Engineering
Classifier: Topic :: Security
Requires-Python: >=3.10
License-File: LICENSE
Requires-Dist: typer>=0.15.0
Requires-Dist: pydantic>=2.11.0
Requires-Dist: psutil>=7.0.0
Requires-Dist: tree-sitter>=0.22.0
Requires-Dist: py-tree-sitter-spthy>=1.2.2
Requires-Dist: diskcache>=5.6.0
Requires-Dist: jinja2>=3.1.0
Requires-Dist: graphviz>=0.20.0
Provides-Extra: dev
Requires-Dist: black>=25.1.0; extra == "dev"
Requires-Dist: isort>=6.0.1; extra == "dev"
Requires-Dist: autoflake>=2.3.1; extra == "dev"
Requires-Dist: pre-commit>=4.2.0; extra == "dev"
Requires-Dist: pre-commit-hooks>=5.0.0; extra == "dev"
Requires-Dist: pytest>=8.3.5; extra == "dev"
Requires-Dist: pytest-asyncio>=1.0.0; extra == "dev"
Requires-Dist: build>=1.0.0; extra == "dev"
Requires-Dist: twine>=6.0.0; extra == "dev"
Requires-Dist: setuptools>=80.0; extra == "dev"
Requires-Dist: wheel>=0.40.0; extra == "dev"
Dynamic: license-file
